lazylabel/__init__.py
lazylabel/__main__.py
lazylabel/main.py
lazylabel/config/__init__.py
lazylabel/config/hotkeys.py
lazylabel/config/paths.py
lazylabel/config/settings.py
lazylabel/core/__init__.py
lazylabel/core/file_manager.py
lazylabel/core/model_manager.py
lazylabel/core/segment_manager.py
lazylabel/models/__init__.py
lazylabel/models/sam2_model.py
lazylabel/models/sam_model.py
lazylabel/ui/__init__.py
lazylabel/ui/control_panel.py
lazylabel/ui/editable_vertex.py
lazylabel/ui/hotkey_dialog.py
lazylabel/ui/hoverable_pixelmap_item.py
lazylabel/ui/hoverable_polygon_item.py
lazylabel/ui/main_window.py
lazylabel/ui/numeric_table_widget_item.py
lazylabel/ui/photo_viewer.py
lazylabel/ui/reorderable_class_table.py
lazylabel/ui/right_panel.py
lazylabel/ui/modes/__init__.py
lazylabel/ui/modes/base_mode.py
lazylabel/ui/modes/multi_view_mode.py
lazylabel/ui/modes/single_view_mode.py
lazylabel/ui/widgets/__init__.py
lazylabel/ui/widgets/adjustments_widget.py
lazylabel/ui/widgets/border_crop_widget.py
lazylabel/ui/widgets/channel_threshold_widget.py
lazylabel/ui/widgets/fft_threshold_widget.py
lazylabel/ui/widgets/fragment_threshold_widget.py
lazylabel/ui/widgets/model_selection_widget.py
lazylabel/ui/widgets/settings_widget.py
lazylabel/ui/widgets/status_bar.py
lazylabel/ui/workers/__init__.py
lazylabel/ui/workers/image_discovery_worker.py
lazylabel/ui/workers/multi_view_sam_init_worker.py
lazylabel/ui/workers/multi_view_sam_update_worker.py
lazylabel/ui/workers/sam_update_worker.py
lazylabel/ui/workers/single_view_sam_init_worker.py
lazylabel/utils/__init__.py
lazylabel/utils/custom_file_system_model.py
lazylabel/utils/fast_file_manager.py
lazylabel/utils/logger.py
lazylabel/utils/utils.py
lazylabel_gui-1.3.9.dist-info/licenses/LICENSE
lazylabel_gui-1.3.9.dist-info/METADATA
lazylabel_gui-1.3.9.dist-info/WHEEL
lazylabel_gui-1.3.9.dist-info/entry_points.txt
lazylabel_gui-1.3.9.dist-info/top_level.txt
lazylabel_gui-1.3.9.dist-info/RECORD
