Metadata-Version: 2.4
Name: lazylabel-gui
Version: 1.3.9
Summary: An image segmentation GUI for generating ML ready mask tensors and annotations.
Author-email: "Deniz N. Cakan" <deniz.n.cakan@gmail.com>
License: MIT License
Project-URL: Homepage, https://github.com/dnzckn/lazylabel
Project-URL: Bug Tracker, https://github.com/dnzckn/lazylabel/issues
Classifier: Programming Language :: Python :: 3
Classifier: License :: OSI Approved :: MIT License
Classifier: Operating System :: OS Independent
Classifier: Topic :: Scientific/Engineering :: Image Processing
Classifier: Environment :: X11 Applications :: Qt
Requires-Python: >=3.10
License-File: LICENSE
Requires-Dist: PyQt6>=6.9.0
Requires-Dist: pyqtdarktheme==2.1.0
Requires-Dist: torch>=2.7.1
Requires-Dist: torchvision>=0.22.1
Requires-Dist: segment-anything==1.0
Requires-Dist: numpy>=2.1.2
Requires-Dist: opencv-python>=4.11.0.86
Requires-Dist: scipy>=1.15.3
Requires-Dist: requests>=2.32.4
Requires-Dist: tqdm>=4.67.1
Provides-Extra: dev
Requires-Dist: pytest>=7.0.0; extra == "dev"
Requires-Dist: pytest-cov>=4.0.0; extra == "dev"
Requires-Dist: pytest-mock>=3.10.0; extra == "dev"
Requires-Dist: pytest-qt>=4.2.0; extra == "dev"
Requires-Dist: ruff>=0.8.0; extra == "dev"
Dynamic: license-file
